gluonts/__init__.py
gluonts/__main__.py
gluonts/env.py
gluonts/exceptions.py
gluonts/gluonts_tqdm.py
gluonts/itertools.py
gluonts/json.py
gluonts/json.pyi
gluonts/maybe.py
gluonts/pydantic.py
gluonts/util.py
gluonts/core/__init__.py
gluonts/core/_base.py
gluonts/core/component.py
gluonts/core/py.typed
gluonts/core/settings.py
gluonts/core/serde/__init__.py
gluonts/core/serde/_base.py
gluonts/core/serde/_dataclass.py
gluonts/core/serde/_json.py
gluonts/core/serde/_parse.py
gluonts/core/serde/flat.py
gluonts/core/serde/np.py
gluonts/core/serde/pd.py
gluonts/dataset/__init__.py
gluonts/dataset/common.py
gluonts/dataset/field_names.py
gluonts/dataset/hierarchical.py
gluonts/dataset/jsonl.py
gluonts/dataset/loader.py
gluonts/dataset/multivariate_grouper.py
gluonts/dataset/pandas.py
gluonts/dataset/split.py
gluonts/dataset/stat.py
gluonts/dataset/util.py
gluonts/dataset/arrow/__init__.py
gluonts/dataset/arrow/__main__.py
gluonts/dataset/arrow/dec.py
gluonts/dataset/arrow/enc.py
gluonts/dataset/arrow/file.py
gluonts/dataset/artificial/__init__.py
gluonts/dataset/artificial/_base.py
gluonts/dataset/artificial/ar_p.py
gluonts/dataset/artificial/recipe.py
gluonts/dataset/repository/__init__.py
gluonts/dataset/repository/_airpassengers.py
gluonts/dataset/repository/_artificial.py
gluonts/dataset/repository/_ercot.py
gluonts/dataset/repository/_ett_small.py
gluonts/dataset/repository/_gp_copula_2019.py
gluonts/dataset/repository/_lstnet.py
gluonts/dataset/repository/_m3.py
gluonts/dataset/repository/_m4.py
gluonts/dataset/repository/_m5.py
gluonts/dataset/repository/_tsf_datasets.py
gluonts/dataset/repository/_tsf_reader.py
gluonts/dataset/repository/_uber_tlc.py
gluonts/dataset/repository/_util.py
gluonts/dataset/repository/datasets.py
gluonts/dataset/schema/__init__.py
gluonts/dataset/schema/translate.py
gluonts/ev/__init__.py
gluonts/ev/aggregations.py
gluonts/ev/metrics.py
gluonts/ev/stats.py
gluonts/ev/ts_stats.py
gluonts/evaluation/__init__.py
gluonts/evaluation/_base.py
gluonts-0.16.2.dist-info/LICENSE
gluonts-0.16.2.dist-info/METADATA
gluonts-0.16.2.dist-info/WHEEL
gluonts-0.16.2.dist-info/entry_points.txt
gluonts-0.16.2.dist-info/top_level.txt
gluonts-0.16.2.dist-info/RECORD
