Metadata-Version: 2.1
Name: gluonts
Version: 0.16.2
Summary: Probabilistic time series modeling in Python.
Home-page: https://github.com/awslabs/gluonts/
Author: Amazon
Author-email: gluon-ts-dev@amazon.com
Maintainer-email: gluon-ts-dev@amazon.com
License: Apache License 2.0
Project-URL: Documentation, https://ts.gluon.ai/stable/
Project-URL: Source Code, https://github.com/awslabs/gluonts/
Requires-Python: >=3.7
Provides-Extra: arrow
Provides-Extra: dev
Provides-Extra: docs
Provides-Extra: mxnet
Provides-Extra: R
Provides-Extra: Prophet
Provides-Extra: pro
Provides-Extra: shell
Provides-Extra: torch
License-File: LICENSE
